{
	"name": "Delete_Execute",
	"properties": {
		"activities": [
			{
				"name": "Delete1",
				"type": "Delete",
				"dependsOn": [],
				"policy": {
					"timeout": "7.00:00:00",
					"retry": 0,
					"retryIntervalInSeconds": 30,
					"secureOutput": false,
					"secureInput": false
				},
				"userProperties": [],
				"typeProperties": {
					"dataset": {
						"referenceName": "DelimitedText3",
						"type": "DatasetReference",
						"parameters": {
							"Filename": "projectoneinput.txt",
							"Foldername": "input"
						}
					},
					"enableLogging": false,
					"storeSettings": {
						"type": "AzureBlobStorageReadSettings",
						"recursive": true,
						"enablePartitionDiscovery": false
					}
				}
			},
			{
				"name": "Execute Pipeline1",
				"type": "ExecutePipeline",
				"dependsOn": [
					{
						"activity": "Delete1",
						"dependencyConditions": [
							"Succeeded"
						]
					}
				],
				"userProperties": [],
				"typeProperties": {
					"pipeline": {
						"referenceName": "DLZ_After_Delete",
						"type": "PipelineReference"
					},
					"waitOnCompletion": true
				}
			}
		],
		"annotations": [],
		"lastPublishTime": "2022-08-14T08:27:27Z"
	},
	"type": "Microsoft.DataFactory/factories/pipelines"
}